[
  {
    "p": "2,953,000",
    "h": "2,960,000",
    "l": "2,949,700",
    "d": "39,100",
    "dp": 1.34,
    "dt": "high",
    "t": "۱۴:۵۷:۲۳",
    "t_en": "14:57:23",
    "t-g": "۱۴:۵۷:۲۳",
    "ts": "2023-12-02 14:57:23"
  },
  {
    "p": "2,968,000",
    "h": "2,985,000",
    "l": "2,954,000",
    "d": "15,000",
    "dp": 0.51,
    "dt": "high",
    "t": "۱۴:۵۳:۰۰",
    "t_en": "14:53:00",
    "t-g": "۱۴:۵۳:۰۰",
    "ts": "2023-12-03 14:53:00"
  },
  {
    "p": "2,984,020",
    "h": "2,989,900",
    "l": "2,955,000",
    "d": "16,020",
    "dp": 0.54,
    "dt": "high",
    "t": "۱۵:۰۰:۰۱",
    "t_en": "15:00:01",
    "t-g": "۱۵:۰۰:۰۱",
    "ts": "2023-12-04 15:00:01"
  },
  {
    "p": "2,949,999",
    "h": "2,950,000",
    "l": "2,939,055",
    "d": "34,021",
    "dp": 1.15,
    "dt": "low",
    "t": "۱۴:۲۳:۵۸",
    "t_en": "14:23:58",
    "t-g": "۱۴:۲۳:۵۸",
    "ts": "2023-12-05 14:23:58"
  },
  {
    "p": "2,941,424",
    "h": "2,955,000",
    "l": "2,927,105",
    "d": "8,575",
    "dp": 0.29,
    "dt": "low",
    "t": "۱۴:۲۸:۱۰",
    "t_en": "14:28:10",
    "t-g": "۱۴:۲۸:۱۰",
    "ts": "2023-12-06 14:28:10"
  },
  {
    "p": "2,941,424",
    "h": "2,955,000",
    "l": "2,927,105",
    "d": "0",
    "dp": 0,
    "dt": "",
    "t": "۱۵ آذر",
    "t_en": " 6 Dec",
    "t-g": "۱۵ آذر",
    "ts": "2023-12-06 00:00:00"
  },
  {
    "p": "2,926,000",
    "h": "2,949,865",
    "l": "2,901,021",
    "d": "15,424",
    "dp": 0.53,
    "dt": "low",
    "t": "۱۴:۴۷:۳۳",
    "t_en": "14:47:33",
    "t-g": "۱۴:۴۷:۳۳",
    "ts": "2023-12-09 14:47:33"
  },
  {
    "p": "2,937,000",
    "h": "2,940,000",
    "l": "2,920,005",
    "d": "11,000",
    "dp": 0.38,
    "dt": "high",
    "t": "۱۴:۴۱:۱۱",
    "t_en": "14:41:11",
    "t-g": "۱۴:۴۱:۱۱",
    "ts": "2023-12-10 14:41:11"
  },
  {
    "p": "2,923,000",
    "h": "2,925,355",
    "l": "2,918,700",
    "d": "14,000",
    "dp": 0.48,
    "dt": "low",
    "t": "۱۵:۰۳:۱۰",
    "t_en": "15:03:10",
    "t-g": "۱۵:۰۳:۱۰",
    "ts": "2023-12-11 15:03:10"
  },
  {
    "p": "2,929,850",
    "h": "2,932,800",
    "l": "2,919,000",
    "d": "6,850",
    "dp": 0.23,
    "dt": "high",
    "t": "۱۴:۵۴:۰۹",
    "t_en": "14:54:09",
    "t-g": "۱۴:۵۴:۰۹",
    "ts": "2023-12-12 14:54:09"
  },
  {
    "p": "2,923,900",
    "h": "2,944,999",
    "l": "2,906,000",
    "d": "5,950",
    "dp": 0.2,
    "dt": "low",
    "t": "۱۴:۴۳:۵۷",
    "t_en": "14:43:57",
    "t-g": "۱۴:۴۳:۵۷",
    "ts": "2023-12-13 14:43:57"
  },
  {
    "p": "2,923,900",
    "h": "2,944,999",
    "l": "2,906,000",
    "d": "0",
    "dp": 0,
    "dt": "",
    "t": "۲۲ آذر",
    "t_en": "13 Dec",
    "t-g": "۲۲ آذر",
    "ts": "2023-12-13 00:00:00"
  },
  {
    "p": "2,922,700",
    "h": "2,932,000",
    "l": "2,921,000",
    "d": "1,200",
    "dp": 0.04,
    "dt": "low",
    "t": "۱۴:۵۹:۰۷",
    "t_en": "14:59:07",
    "t-g": "۱۴:۵۹:۰۷",
    "ts": "2023-12-16 14:59:07"
  },
  {
    "p": "2,925,000",
    "h": "2,933,776",
    "l": "2,920,055",
    "d": "2,300",
    "dp": 0.08,
    "dt": "high",
    "t": "۱۴:۵۱:۵۹",
    "t_en": "14:51:59",
    "t-g": "۱۴:۵۱:۵۹",
    "ts": "2023-12-18 14:51:59"
  },
  {
    "p": "2,919,000",
    "h": "2,920,000",
    "l": "2,910,001",
    "d": "6,000",
    "dp": 0.21,
    "dt": "low",
    "t": "۱۵:۰۵:۱۱",
    "t_en": "15:05:11",
    "t-g": "۱۵:۰۵:۱۱",
    "ts": "2023-12-19 15:05:11"
  },
  {
    "p": "2,936,650",
    "h": "2,938,000",
    "l": "2,912,003",
    "d": "17,650",
    "dp": 0.6,
    "dt": "high",
    "t": "۱۴:۲۶:۱۴",
    "t_en": "14:26:14",
    "t-g": "۱۴:۲۶:۱۴",
    "ts": "2023-12-20 14:26:14"
  },
  {
    "p": "2,936,650",
    "h": "2,938,000",
    "l": "2,912,003",
    "d": "0",
    "dp": 0,
    "dt": "",
    "t": "۲۹ آذر",
    "t_en": "20 Dec",
    "t-g": "۲۹ آذر",
    "ts": "2023-12-20 00:00:00"
  },
  {
    "p": "2,947,500",
    "h": "2,949,000",
    "l": "2,930,501",
    "d": "10,850",
    "dp": 0.37,
    "dt": "high",
    "t": "۱۵:۰۱:۰۵",
    "t_en": "15:01:05",
    "t-g": "۱۵:۰۱:۰۵",
    "ts": "2023-12-23 15:01:05"
  },
  {
    "p": "2,936,004",
    "h": "2,947,376",
    "l": "2,935,005",
    "d": "11,496",
    "dp": 0.39,
    "dt": "low",
    "t": "۱۵:۰۲:۳۴",
    "t_en": "15:02:34",
    "t-g": "۱۵:۰۲:۳۴",
    "ts": "2023-12-24 15:02:34"
  },
  {
    "p": "2,934,000",
    "h": "2,934,000",
    "l": "2,934,000",
    "d": "15,000",
    "dp": 0.51,
    "dt": "high",
    "t": "۲۰:۲۶:۰۶",
    "t_en": "20:26:06",
    "t-g": "۲۰:۲۶:۰۶",
    "ts": "2023-12-25 20:26:06"
  },
  {
    "p": "2,945,000",
    "h": "2,948,500",
    "l": "2,935,000",
    "d": "11,000",
    "dp": 0.37,
    "dt": "high",
    "t": "۱۵:۰۰:۱۳",
    "t_en": "15:00:13",
    "t-g": "۱۵:۰۰:۱۳",
    "ts": "2023-12-26 15:00:13"
  },
  {
    "p": "2,948,900",
    "h": "2,949,000",
    "l": "2,940,055",
    "d": "3,900",
    "dp": 0.13,
    "dt": "high",
    "t": "۱۴:۵۸:۱۱",
    "t_en": "14:58:11",
    "t-g": "۱۴:۵۸:۱۱",
    "ts": "2023-12-27 14:58:11"
  },
  {
    "p": "2,948,900",
    "h": "2,949,000",
    "l": "2,940,055",
    "d": "0",
    "dp": 0,
    "dt": "",
    "t": "۶ دی",
    "t_en": "27 Dec",
    "t-g": "۶ دی",
    "ts": "2023-12-27 00:00:00"
  },
  {
    "p": "2,970,002",
    "h": "2,986,931",
    "l": "2,945,211",
    "d": "21,102",
    "dp": 0.72,
    "dt": "high",
    "t": "۱۵:۰۰:۴۵",
    "t_en": "15:00:45",
    "t-g": "۱۵:۰۰:۴۵",
    "ts": "2023-12-30 15:00:45"
  },
  {
    "p": "2,975,000",
    "h": "2,978,900",
    "l": "2,964,130",
    "d": "4,998",
    "dp": 0.17,
    "dt": "high",
    "t": "۱۴:۴۲:۳۰",
    "t_en": "14:42:30",
    "t-g": "۱۴:۴۲:۳۰",
    "ts": "2023-12-31 14:42:30"
  },
  {
    "p": "2,978,000",
    "h": "2,979,500",
    "l": "2,970,000",
    "d": "3,000",
    "dp": 0.1,
    "dt": "high",
    "t": "۱۵:۰۱:۱۵",
    "t_en": "15:01:15",
    "t-g": "۱۵:۰۱:۱۵",
    "ts": "2024-01-01 15:01:15"
  },
  {
    "p": "3,020,000",
    "h": "3,020,000",
    "l": "2,978,005",
    "d": "42,000",
    "dp": 1.41,
    "dt": "high",
    "t": "۱۴:۵۷:۳۱",
    "t_en": "14:57:31",
    "t-g": "۱۴:۵۷:۳۱",
    "ts": "2024-01-02 14:57:31"
  },
  {
    "p": "3,017,000",
    "h": "3,049,777",
    "l": "3,012,599",
    "d": "3,000",
    "dp": 0.1,
    "dt": "low",
    "t": "۱۵:۰۲:۱۲",
    "t_en": "15:02:12",
    "t-g": "۱۵:۰۲:۱۲",
    "ts": "2024-01-03 15:02:12"
  },
  {
    "p": "3,017,000",
    "h": "3,049,777",
    "l": "3,012,599",
    "d": "0",
    "dp": 0,
    "dt": "",
    "t": "۱۳ دی",
    "t_en": " 3 Jan",
    "t-g": "۱۳ دی",
    "ts": "2024-01-03 00:00:00"
  },
  {
    "p": "3,022,000",
    "h": "3,022,000",
    "l": "3,010,000",
    "d": "5,000",
    "dp": 0.17,
    "dt": "high",
    "t": "۱۴:۲۹:۰۲",
    "t_en": "14:29:02",
    "t-g": "۱۴:۲۹:۰۲",
    "ts": "2024-01-06 14:29:02"
  },
  {
    "p": "3,057,899",
    "h": "3,069,499",
    "l": "3,024,000",
    "d": "35,899",
    "dp": 1.19,
    "dt": "high",
    "t": "۱۴:۵۹:۳۵",
    "t_en": "14:59:35",
    "t-g": "۱۴:۵۹:۳۵",
    "ts": "2024-01-07 14:59:35"
  },
  {
    "p": "3,046,000",
    "h": "3,075,000",
    "l": "3,043,979",
    "d": "11,899",
    "dp": 0.39,
    "dt": "low",
    "t": "۱۴:۵۷:۱۳",
    "t_en": "14:57:13",
    "t-g": "۱۴:۵۷:۱۳",
    "ts": "2024-01-08 14:57:13"
  },
  {
    "p": "3,094,000",
    "h": "3,094,000",
    "l": "3,047,199",
    "d": "48,000",
    "dp": 1.58,
    "dt": "high",
    "t": "۱۴:۵۹:۴۱",
    "t_en": "14:59:41",
    "t-g": "۱۴:۵۹:۴۱",
    "ts": "2024-01-09 14:59:41"
  },
  {
    "p": "3,223,000",
    "h": "3,229,998",
    "l": "3,183,944",
    "d": "129,000",
    "dp": 4.17,
    "dt": "high",
    "t": "۱۵:۰۱:۰۵",
    "t_en": "15:01:05",
    "t-g": "۱۵:۰۱:۰۵",
    "ts": "2024-01-10 15:01:05"
  },
  {
    "p": "3,223,000",
    "h": "3,229,998",
    "l": "3,183,944",
    "d": "0",
    "dp": 0,
    "dt": "",
    "t": "۲۰ دی",
    "t_en": "10 Jan",
    "t-g": "۲۰ دی",
    "ts": "2024-01-10 00:00:00"
  },
  {
    "p": "3,324,030",
    "h": "3,350,000",
    "l": "3,270,200",
    "d": "101,030",
    "dp": 3.13,
    "dt": "high",
    "t": "۱۵:۰۲:۲۶",
    "t_en": "15:02:26",
    "t-g": "۱۵:۰۲:۲۶",
    "ts": "2024-01-13 15:02:26"
  },
  {
    "p": "3,182,501",
    "h": "3,424,000",
    "l": "3,146,000",
    "d": "141,529",
    "dp": 4.45,
    "dt": "low",
    "t": "۱۵:۰۱:۱۸",
    "t_en": "15:01:18",
    "t-g": "۱۵:۰۱:۱۸",
    "ts": "2024-01-14 15:01:18"
  },
  {
    "p": "3,138,122",
    "h": "3,157,732",
    "l": "3,114,000",
    "d": "44,379",
    "dp": 1.41,
    "dt": "low",
    "t": "۱۴:۵۸:۱۹",
    "t_en": "14:58:19",
    "t-g": "۱۴:۵۸:۱۹",
    "ts": "2024-01-15 14:58:19"
  },
  {
    "p": "3,182,000",
    "h": "3,210,000",
    "l": "3,160,009",
    "d": "43,878",
    "dp": 1.4,
    "dt": "high",
    "t": "۱۴:۵۸:۱۶",
    "t_en": "14:58:16",
    "t-g": "۱۴:۵۸:۱۶",
    "ts": "2024-01-16 14:58:16"
  },
  {
    "p": "3,156,841",
    "h": "3,156,841",
    "l": "3,130,100",
    "d": "25,159",
    "dp": 0.8,
    "dt": "low",
    "t": "۱۴:۵۷:۰۰",
    "t_en": "14:57:00",
    "t-g": "۱۴:۵۷:۰۰",
    "ts": "2024-01-17 14:57:00"
  }
]
