[
  {
    "p": "71,300",
    "h": "71,600",
    "l": "70,800",
    "d": "0",
    "dp": 0,
    "dt": "",
    "t": "۱۹:۵۵:۳۴",
    "t_en": "19:55:34",
    "t-g": "۱۹:۵۵:۳۴",
    "ts": "2023-12-02 19:55:34"
  },
  {
    "p": "71,500",
    "h": "71,700",
    "l": "70,700",
    "d": "200",
    "dp": 0.28,
    "dt": "high",
    "t": "۱۷:۲۹:۳۸",
    "t_en": "17:29:38",
    "t-g": "۱۷:۲۹:۳۸",
    "ts": "2023-12-03 17:29:38"
  },
  {
    "p": "71,600",
    "h": "71,700",
    "l": "71,500",
    "d": "100",
    "dp": 0.14,
    "dt": "high",
    "t": "۱۷:۳۰:۴۱",
    "t_en": "17:30:41",
    "t-g": "۱۷:۳۰:۴۱",
    "ts": "2023-12-04 17:30:41"
  },
  {
    "p": "71,400",
    "h": "71,600",
    "l": "71,300",
    "d": "300",
    "dp": 0.42,
    "dt": "low",
    "t": "۱۷:۰۶:۴۸",
    "t_en": "17:06:48",
    "t-g": "۱۷:۰۶:۴۸",
    "ts": "2023-12-05 17:06:48"
  },
  {
    "p": "71,000",
    "h": "71,400",
    "l": "71,000",
    "d": "400",
    "dp": 0.56,
    "dt": "low",
    "t": "۱۶:۵۳:۲۷",
    "t_en": "16:53:27",
    "t-g": "۱۶:۵۳:۲۷",
    "ts": "2023-12-06 16:53:27"
  },
  {
    "p": "71,300",
    "h": "71,400",
    "l": "71,200",
    "d": "200",
    "dp": 0.28,
    "dt": "high",
    "t": "۱۶:۵۰:۴۷",
    "t_en": "16:50:47",
    "t-g": "۱۶:۵۰:۴۷",
    "ts": "2023-12-07 16:50:47"
  },
  {
    "p": "71,300",
    "h": "71,400",
    "l": "71,200",
    "d": "0",
    "dp": 0,
    "dt": "",
    "t": "۱۶ آذر",
    "t_en": " 7 Dec",
    "t-g": "۱۶ آذر",
    "ts": "2023-12-07 00:00:00"
  },
  {
    "p": "71,300",
    "h": "71,500",
    "l": "71,200",
    "d": "0",
    "dp": 0,
    "dt": "",
    "t": "۱۷:۳۴:۰۵",
    "t_en": "17:34:05",
    "t-g": "۱۷:۳۴:۰۵",
    "ts": "2023-12-09 17:34:05"
  },
  {
    "p": "71,400",
    "h": "71,500",
    "l": "71,200",
    "d": "0",
    "dp": 0,
    "dt": "",
    "t": "۱۷:۳۴:۳۶",
    "t_en": "17:34:36",
    "t-g": "۱۷:۳۴:۳۶",
    "ts": "2023-12-10 17:34:36"
  },
  {
    "p": "71,400",
    "h": "71,500",
    "l": "71,300",
    "d": "100",
    "dp": 0.14,
    "dt": "high",
    "t": "۱۹:۵۸:۰۰",
    "t_en": "19:58:00",
    "t-g": "۱۹:۵۸:۰۰",
    "ts": "2023-12-11 19:58:00"
  },
  {
    "p": "70,500",
    "h": "71,500",
    "l": "70,500",
    "d": "900",
    "dp": 1.28,
    "dt": "low",
    "t": "۱۹:۵۶:۴۷",
    "t_en": "19:56:47",
    "t-g": "۱۹:۵۶:۴۷",
    "ts": "2023-12-12 19:56:47"
  },
  {
    "p": "70,500",
    "h": "70,600",
    "l": "70,400",
    "d": "0",
    "dp": 0,
    "dt": "",
    "t": "۱۹:۲۵:۲۴",
    "t_en": "19:25:24",
    "t-g": "۱۹:۲۵:۲۴",
    "ts": "2023-12-13 19:25:24"
  },
  {
    "p": "70,600",
    "h": "70,600",
    "l": "70,500",
    "d": "100",
    "dp": 0.14,
    "dt": "high",
    "t": "۱۶:۵۶:۰۹",
    "t_en": "16:56:09",
    "t-g": "۱۶:۵۶:۰۹",
    "ts": "2023-12-14 16:56:09"
  },
  {
    "p": "70,600",
    "h": "70,600",
    "l": "70,500",
    "d": "0",
    "dp": 0,
    "dt": "",
    "t": "۲۳ آذر",
    "t_en": "14 Dec",
    "t-g": "۲۳ آذر",
    "ts": "2023-12-14 00:00:00"
  },
  {
    "p": "70,900",
    "h": "71,000",
    "l": "70,800",
    "d": "300",
    "dp": 0.42,
    "dt": "high",
    "t": "۱۹:۲۲:۴۷",
    "t_en": "19:22:47",
    "t-g": "۱۹:۲۲:۴۷",
    "ts": "2023-12-16 19:22:47"
  }
]
