[
  {
    "p": "281,000",
    "h": "281,100",
    "l": "280,300",
    "d": "500",
    "dp": 0.18,
    "dt": "high",
    "t": "۱۹:۵۵:۵۲",
    "t_en": "19:55:52",
    "t-g": "۱۹:۵۵:۵۲",
    "ts": "2023-12-11 19:55:52"
  },
  {
    "p": "281,000",
    "h": "281,100",
    "l": "280,300",
    "d": "0",
    "dp": 0,
    "dt": "",
    "t": "۲۰ آذر",
    "t_en": "11 Dec",
    "t-g": "۲۰ آذر",
    "ts": "2023-12-11 00:00:00"
  },
  {
    "p": "280,500",
    "h": "281,200",
    "l": "280,300",
    "d": "500",
    "dp": 0.18,
    "dt": "low",
    "t": "۱۳:۵۸:۲۷",
    "t_en": "13:58:27",
    "t-g": "۱۳:۵۸:۲۷",
    "ts": "2023-12-12 13:58:27"
  },
  {
    "p": "280,500",
    "h": "281,200",
    "l": "280,300",
    "d": "500",
    "dp": 0.18,
    "dt": "low",
    "t": "۱۵:۰۲:۲۵",
    "t_en": "15:02:25",
    "t-g": "۱۵:۰۲:۲۵",
    "ts": "2023-12-12 15:02:25"
  },
  {
    "p": "280,400",
    "h": "281,200",
    "l": "280,300",
    "d": "600",
    "dp": 0.21,
    "dt": "low",
    "t": "۱۶:۱۷:۵۶",
    "t_en": "16:17:56",
    "t-g": "۱۶:۱۷:۵۶",
    "ts": "2023-12-12 16:17:56"
  },
  {
    "p": "280,400",
    "h": "281,200",
    "l": "280,100",
    "d": "600",
    "dp": 0.21,
    "dt": "low",
    "t": "۱۷:۱۸:۰۹",
    "t_en": "17:18:09",
    "t-g": "۱۷:۱۸:۰۹",
    "ts": "2023-12-12 17:18:09"
  },
  {
    "p": "280,300",
    "h": "281,200",
    "l": "280,100",
    "d": "700",
    "dp": 0.25,
    "dt": "low",
    "t": "۱۸:۳۸:۱۹",
    "t_en": "18:38:19",
    "t-g": "۱۸:۳۸:۱۹",
    "ts": "2023-12-12 18:38:19"
  },
  {
    "p": "280,100",
    "h": "281,200",
    "l": "280,100",
    "d": "900",
    "dp": 0.32,
    "dt": "low",
    "t": "۱۹:۵۸:۴۹",
    "t_en": "19:58:49",
    "t-g": "۱۹:۵۸:۴۹",
    "ts": "2023-12-12 19:58:49"
  },
  {
    "p": "280,100",
    "h": "281,200",
    "l": "280,100",
    "d": "0",
    "dp": 0,
    "dt": "",
    "t": "۲۱ آذر",
    "t_en": "12 Dec",
    "t-g": "۲۱ آذر",
    "ts": "2023-12-12 00:00:00"
  },
  {
    "p": "280,000",
    "h": "280,200",
    "l": "279,800",
    "d": "100",
    "dp": 0.04,
    "dt": "low",
    "t": "۱۳:۱۶:۳۹",
    "t_en": "13:16:39",
    "t-g": "۱۳:۱۶:۳۹",
    "ts": "2023-12-13 13:16:39"
  },
  {
    "p": "279,600",
    "h": "280,200",
    "l": "279,600",
    "d": "500",
    "dp": 0.18,
    "dt": "low",
    "t": "۱۴:۴۸:۲۴",
    "t_en": "14:48:24",
    "t-g": "۱۴:۴۸:۲۴",
    "ts": "2023-12-13 14:48:24"
  },
  {
    "p": "279,900",
    "h": "280,200",
    "l": "279,600",
    "d": "200",
    "dp": 0.07,
    "dt": "low",
    "t": "۱۵:۵۸:۵۳",
    "t_en": "15:58:53",
    "t-g": "۱۵:۵۸:۵۳",
    "ts": "2023-12-13 15:58:53"
  },
  {
    "p": "279,900",
    "h": "280,200",
    "l": "279,600",
    "d": "200",
    "dp": 0.07,
    "dt": "low",
    "t": "۱۶:۵۹:۵۸",
    "t_en": "16:59:58",
    "t-g": "۱۶:۵۹:۵۸",
    "ts": "2023-12-13 16:59:58"
  },
  {
    "p": "279,800",
    "h": "280,200",
    "l": "279,600",
    "d": "300",
    "dp": 0.11,
    "dt": "low",
    "t": "۱۸:۰۷:۲۴",
    "t_en": "18:07:24",
    "t-g": "۱۸:۰۷:۲۴",
    "ts": "2023-12-13 18:07:24"
  },
  {
    "p": "280,100",
    "h": "280,200",
    "l": "279,600",
    "d": "0",
    "dp": 0,
    "dt": "",
    "t": "۱۹:۱۷:۵۴",
    "t_en": "19:17:54",
    "t-g": "۱۹:۱۷:۵۴",
    "ts": "2023-12-13 19:17:54"
  },
  {
    "p": "280,100",
    "h": "280,200",
    "l": "279,600",
    "d": "0",
    "dp": 0,
    "dt": "",
    "t": "۱۹:۵۸:۰۱",
    "t_en": "19:58:01",
    "t-g": "۱۹:۵۸:۰۱",
    "ts": "2023-12-13 19:58:01"
  },
  {
    "p": "280,100",
    "h": "280,200",
    "l": "279,600",
    "d": "0",
    "dp": 0,
    "dt": "",
    "t": "۲۲ آذر",
    "t_en": "13 Dec",
    "t-g": "۲۲ آذر",
    "ts": "2023-12-13 00:00:00"
  },
  {
    "p": "280,200",
    "h": "280,500",
    "l": "279,900",
    "d": "100",
    "dp": 0.04,
    "dt": "high",
    "t": "۱۲:۵۶:۳۸",
    "t_en": "12:56:38",
    "t-g": "۱۲:۵۶:۳۸",
    "ts": "2023-12-14 12:56:38"
  },
  {
    "p": "280,100",
    "h": "280,500",
    "l": "279,900",
    "d": "0",
    "dp": 0,
    "dt": "",
    "t": "۱۴:۵۷:۳۲",
    "t_en": "14:57:32",
    "t-g": "۱۴:۵۷:۳۲",
    "ts": "2023-12-14 14:57:32"
  },
  {
    "p": "280,200",
    "h": "280,500",
    "l": "279,900",
    "d": "100",
    "dp": 0.04,
    "dt": "high",
    "t": "۱۵:۵۵:۲۹",
    "t_en": "15:55:29",
    "t-g": "۱۵:۵۵:۲۹",
    "ts": "2023-12-14 15:55:29"
  },
  {
    "p": "280,200",
    "h": "280,500",
    "l": "279,900",
    "d": "100",
    "dp": 0.04,
    "dt": "high",
    "t": "۱۶:۵۹:۲۵",
    "t_en": "16:59:25",
    "t-g": "۱۶:۵۹:۲۵",
    "ts": "2023-12-14 16:59:25"
  },
  {
    "p": "280,200",
    "h": "280,500",
    "l": "279,900",
    "d": "0",
    "dp": 0,
    "dt": "",
    "t": "۲۳ آذر",
    "t_en": "14 Dec",
    "t-g": "۲۳ آذر",
    "ts": "2023-12-14 00:00:00"
  },
  {
    "p": "280,400",
    "h": "280,700",
    "l": "280,200",
    "d": "200",
    "dp": 0.07,
    "dt": "high",
    "t": "۱۲:۵۹:۲۴",
    "t_en": "12:59:24",
    "t-g": "۱۲:۵۹:۲۴",
    "ts": "2023-12-16 12:59:24"
  },
  {
    "p": "280,300",
    "h": "280,700",
    "l": "280,200",
    "d": "100",
    "dp": 0.04,
    "dt": "high",
    "t": "۱۴:۰۸:۲۶",
    "t_en": "14:08:26",
    "t-g": "۱۴:۰۸:۲۶",
    "ts": "2023-12-16 14:08:26"
  },
  {
    "p": "280,200",
    "h": "280,700",
    "l": "280,100",
    "d": "0",
    "dp": 0,
    "dt": "",
    "t": "۱۵:۲۰:۵۷",
    "t_en": "15:20:57",
    "t-g": "۱۵:۲۰:۵۷",
    "ts": "2023-12-16 15:20:57"
  },
  {
    "p": "280,100",
    "h": "280,700",
    "l": "280,100",
    "d": "100",
    "dp": 0.04,
    "dt": "low",
    "t": "۱۶:۲۵:۱۹",
    "t_en": "16:25:19",
    "t-g": "۱۶:۲۵:۱۹",
    "ts": "2023-12-16 16:25:19"
  },
  {
    "p": "280,000",
    "h": "280,700",
    "l": "280,000",
    "d": "200",
    "dp": 0.07,
    "dt": "low",
    "t": "۱۷:۱۵:۰۱",
    "t_en": "17:15:01",
    "t-g": "۱۷:۱۵:۰۱",
    "ts": "2023-12-16 17:15:01"
  },
  {
    "p": "280,100",
    "h": "280,700",
    "l": "280,000",
    "d": "100",
    "dp": 0.04,
    "dt": "low",
    "t": "۱۸:۲۵:۴۳",
    "t_en": "18:25:43",
    "t-g": "۱۸:۲۵:۴۳",
    "ts": "2023-12-16 18:25:43"
  },
  {
    "p": "280,300",
    "h": "280,700",
    "l": "280,000",
    "d": "100",
    "dp": 0.04,
    "dt": "high",
    "t": "۱۹:۲۵:۴۹",
    "t_en": "19:25:49",
    "t-g": "۱۹:۲۵:۴۹",
    "ts": "2023-12-16 19:25:49"
  },
  {
    "p": "280,100",
    "h": "280,700",
    "l": "280,000",
    "d": "100",
    "dp": 0.04,
    "dt": "low",
    "t": "۱۹:۵۹:۴۶",
    "t_en": "19:59:46",
    "t-g": "۱۹:۵۹:۴۶",
    "ts": "2023-12-16 19:59:46"
  },
  {
    "p": "280,100",
    "h": "280,700",
    "l": "280,000",
    "d": "0",
    "dp": 0,
    "dt": "",
    "t": "۲۵ آذر",
    "t_en": "16 Dec",
    "t-g": "۲۵ آذر",
    "ts": "2023-12-16 00:00:00"
  },
  {
    "p": "280,200",
    "h": "280,400",
    "l": "279,800",
    "d": "100",
    "dp": 0.04,
    "dt": "high",
    "t": "۱۳:۲۹:۳۷",
    "t_en": "13:29:37",
    "t-g": "۱۳:۲۹:۳۷",
    "ts": "2023-12-17 13:29:37"
  },
  {
    "p": "280,400",
    "h": "280,400",
    "l": "279,800",
    "d": "300",
    "dp": 0.11,
    "dt": "high",
    "t": "۱۴:۴۸:۳۳",
    "t_en": "14:48:33",
    "t-g": "۱۴:۴۸:۳۳",
    "ts": "2023-12-17 14:48:33"
  },
  {
    "p": "280,200",
    "h": "280,500",
    "l": "279,800",
    "d": "100",
    "dp": 0.04,
    "dt": "high",
    "t": "۱۵:۵۷:۰۰",
    "t_en": "15:57:00",
    "t-g": "۱۵:۵۷:۰۰",
    "ts": "2023-12-17 15:57:00"
  },
  {
    "p": "280,200",
    "h": "280,500",
    "l": "279,800",
    "d": "100",
    "dp": 0.04,
    "dt": "high",
    "t": "۱۶:۵۶:۰۰",
    "t_en": "16:56:00",
    "t-g": "۱۶:۵۶:۰۰",
    "ts": "2023-12-17 16:56:00"
  },
  {
    "p": "280,200",
    "h": "280,500",
    "l": "279,800",
    "d": "100",
    "dp": 0.04,
    "dt": "high",
    "t": "۱۷:۵۶:۴۷",
    "t_en": "17:56:47",
    "t-g": "۱۷:۵۶:۴۷",
    "ts": "2023-12-17 17:56:47"
  },
  {
    "p": "280,200",
    "h": "280,500",
    "l": "279,800",
    "d": "100",
    "dp": 0.04,
    "dt": "high",
    "t": "۱۹:۰۰:۰۰",
    "t_en": "19:00:00",
    "t-g": "۱۹:۰۰:۰۰",
    "ts": "2023-12-17 19:00:00"
  },
  {
    "p": "280,200",
    "h": "280,500",
    "l": "279,800",
    "d": "100",
    "dp": 0.04,
    "dt": "high",
    "t": "۱۹:۵۸:۴۱",
    "t_en": "19:58:41",
    "t-g": "۱۹:۵۸:۴۱",
    "ts": "2023-12-17 19:58:41"
  }
]
